recognizers_number/__init__.py
recognizers_number/culture.py
recognizers_number/number/__init__.py
recognizers_number/number/cjk_parsers.py
recognizers_number/number/constants.py
recognizers_number/number/extractors.py
recognizers_number/number/models.py
recognizers_number/number/number_options.py
recognizers_number/number/number_recognizer.py
recognizers_number/number/parser_factory.py
recognizers_number/number/parsers.py
recognizers_number/number/chinese/__init__.py
recognizers_number/number/chinese/extractors.py
recognizers_number/number/chinese/parsers.py
recognizers_number/number/english/__init__.py
recognizers_number/number/english/extractors.py
recognizers_number/number/english/parsers.py
recognizers_number/number/french/__init__.py
recognizers_number/number/french/extractors.py
recognizers_number/number/french/parsers.py
recognizers_number/number/japanese/__init__.py
recognizers_number/number/japanese/extractors.py
recognizers_number/number/japanese/parsers.py
recognizers_number/number/portuguese/__init__.py
recognizers_number/number/portuguese/extractors.py
recognizers_number/number/portuguese/parsers.py
recognizers_number/number/spanish/__init__.py
recognizers_number/number/spanish/extractors.py
recognizers_number/number/spanish/parsers.py
recognizers_number/resources/__init__.py
recognizers_number/resources/base_numbers.py
recognizers_number/resources/chinese_numeric.py
recognizers_number/resources/english_numeric.py
recognizers_number/resources/french_numeric.py
recognizers_number/resources/japanese_numeric.py
recognizers_number/resources/portuguese_numeric.py
recognizers_number/resources/spanish_numeric.py
recognizers_text_number-1.0.2a2.dist-info/METADATA
recognizers_text_number-1.0.2a2.dist-info/WHEEL
recognizers_text_number-1.0.2a2.dist-info/top_level.txt
recognizers_text_number-1.0.2a2.dist-info/RECORD
